.gitignore
.travis.yml
LICENSE
MANIFEST.in
README.md
README.rst
pytest.ini
requirements.txt
setup.py
magic_parameter/__init__.py
magic_parameter/argument_processing.py
magic_parameter/decorator.py
magic_parameter/exception.py
magic_parameter/metadata.py
magic_parameter/parameter_declaration.py
magic_parameter/type_declaration.py
magic_parameter/utils.py
magic_parameter.egg-info/PKG-INFO
magic_parameter.egg-info/SOURCES.txt
magic_parameter.egg-info/dependency_links.txt
magic_parameter.egg-info/entry_points.txt
magic_parameter.egg-info/requires.txt
magic_parameter.egg-info/top_level.txt
scripts/install-from-source.sh
scripts/install-from-yum.sh
scripts/pip-install-pkgs-of-requirements.sh
scripts/push-to-pypi.sh
scripts/update-readme-rst.sh
tests/test_from_restdef.py
tests/test_type_declaration.py
tests/test_usage.py
tests/__pycache__/test_from_restdef.cpython-35-PYTEST.pyc
tests/__pycache__/test_main.cpython-35-PYTEST.pyc
tests/__pycache__/test_type_declaration.cpython-27-PYTEST.pyc
tests/__pycache__/test_type_declaration.cpython-35-PYTEST.pyc
tests/__pycache__/test_type_declearation.cpython-35-PYTEST.pyc
tests/__pycache__/test_usage.cpython-27-PYTEST.pyc
tests/__pycache__/test_usage.cpython-35-PYTEST.pyc
tests/__pycache__/test_utils.cpython-35-PYTEST.pyc